simplex/__init__.py
simplex/_src/__init__.py
simplex/_src/simplex.py
nsimplex-0.0.1.dist-info/METADATA
nsimplex-0.0.1.dist-info/WHEEL
nsimplex-0.0.1.dist-info/top_level.txt
nsimplex-0.0.1.dist-info/RECORD
