Metadata-Version: 2.1
Name: nsimplex
Version: 0.0.1
Summary: A python package that implements the geometric object of a simplex.
Home-page: https://github.com/killiansheriff/simplex
Author: Killian Sheriff
Author-email: ksheriff@mit.edu
License: MIT
Requires-Dist: numpy
